drf_extended_viewset/__init__.py
drf_extended_viewset/drf_extended_viewset.py
drf_extended_viewset-0.1.1.dist-info/AUTHORS.rst
drf_extended_viewset-0.1.1.dist-info/LICENSE
drf_extended_viewset-0.1.1.dist-info/METADATA
drf_extended_viewset-0.1.1.dist-info/WHEEL
drf_extended_viewset-0.1.1.dist-info/top_level.txt
drf_extended_viewset-0.1.1.dist-info/RECORD
