Metadata-Version: 2.1
Name: drf-extended-viewset
Version: 0.1.1
Summary: Django Rest Framework extension for implement by action serializers, permissions & /etc
Home-page: https://github.com/ivlevdenis/drf_extended_viewset
Author: Denis Ivlev
Author-email: me@dierz.pro
License: MIT license
Keywords: drf_extended_viewset
Platform: UNKNOWN
Classifier: Development Status :: 2 - Pre-Alpha
Classifier: Intended Audience :: Developers
Classifier: License :: OSI Approved :: MIT License
Classifier: Natural Language :: English
Classifier: Programming Language :: Python :: 3
Classifier: Programming Language :: Python :: 3.5
Classifier: Programming Language :: Python :: 3.6
Classifier: Programming Language :: Python :: 3.7
Classifier: Programming Language :: Python :: 3.8
Requires-Python: >=3.5
Requires-Dist: djangorestframework (>=3.10)
